Workbook

Sheet Assumptions
A1: JHI Research & Analytics Firm, Inc.
A2: Prepaid-MSA Sales Commission — assumptions
A3: generated 2026-07-30 · JHI-SIG: 69M2705M
A5: Tier 1 price ($/mo) | B5: 1500 | C5: Enterprise / Family Office
A6: Tier 2 price ($/mo) | B6: 299 | C6: Professional
A7: Tier 1 mix (% of closes) | B7: 10 | C7: Share of closes that are Tier 1
A8: Closes per month | B8: 100 | C8: New full-paid subs signed each month
A9: Annual prepay discount (%) | B9: 10 | C9: Discount for paying 12 months up front
A10: Upfront commission rate (%) | B10: 15 | C10: Rep % of full-paid (net) contract value, at signing
A11: MSA completion / renewal rate (%) | B11: 90 | C11: Share of contracts that complete the full 12-mo MSA
A12: Year-end MSA-completion bonus rate (%) | B12: 5 | C12: Rep bonus % of completed-contract value, paid at year-end
A14: DERIVED
A15: Subscriptions per year | B15: =B8*12 | C15: Closes/mo × 12 (e.g. 100 → 1,200)
A16: Avg full-paid price / sub (net, annual) | B16: =((B5*B7/100)+(B6*(1-B7/100)))*12*(1-B9/100) | C16: Blended monthly price × 12 × (1 − prepay discount)
A17: Total prepaid annual revenue (net) | B17: =B15*B16
A19: OPERATING ASSUMPTIONS (editable)
A20: Payment processing (% of revenue) | B20: 3
A21: Infra / support (% of revenue) | B21: 2
A22: Data license — SF1 ($/yr, fixed) | B22: 18000
A23: Marketing ($/yr) | B23: 36000
A24: Legal & accounting ($/yr) | B24: 18000
A25: Software & AI tools ($/yr) | B25: 12000
A26: Founder / ops comp ($/yr) | B26: 60000

Sheet Upfront Commission (15%)
A1: JHI Research & Analytics Firm, Inc.
A2: Upfront commission — 15% of full-paid (net) contract value
A3: generated 2026-07-30 · JHI-SIG: 69M2705M
A4: Contracts are prepaid annual (12-mo MSA). Rep earns the upfront commission at signing on the net (post-discount) contract value. Pay on collected cash.
B5: Tier 1 | C5: Tier 2 | D5: Total
A6: Subscriptions / year | B6: =Assumptions!$B$15*Assumptions!$B$7/100 | C6: =Assumptions!$B$15*(1-Assumptions!$B$7/100) | D6: =B6+C6
A7: Full-paid price / sub (net, annual) | B7: =Assumptions!$B$5*12*(1-Assumptions!$B$9/100) | C7: =Assumptions!$B$6*12*(1-Assumptions!$B$9/100)
A8: Prepaid annual revenue (net) | B8: =B6*B7 | C8: =C6*C7 | D8: =B8+C8
A9: Upfront commission / sub (15%) | B9: =B7*Assumptions!$B$10/100 | C9: =C7*Assumptions!$B$10/100
A10: Upfront commission (total) | B10: =B8*Assumptions!$B$10/100 | C10: =C8*Assumptions!$B$10/100 | D10: =B10+C10
A13: Cash-flow note: 15% paid UP FRONT on the full annual contract is front-loaded vs. a monthly residual — model the cash outlay at signing.

Sheet Year-End MSA Bonus
A1: JHI Research & Analytics Firm, Inc.
A2: Year-end MSA-completion bonus
A3: generated 2026-07-30 · JHI-SIG: 69M2705M
A4: Additional bonus rewarding contracts that COMPLETE the full 12-month MSA term (retention). Paid at year-end on completed-contract value.
A5: Subscriptions / year (signed) | B5: =Assumptions!$B$15 | C5: From Assumptions (closes/mo × 12)
A6: MSA completion / renewal rate | B6: =Assumptions!$B$11/100 | C6: Share completing the full 12-mo term
A7: Contracts completing full 12-mo MSA | B7: =B5*B6 | C7: Signed × completion rate
A8: Completed-contract value (net) | B8: =Assumptions!$B$17*B6 | C8: Total prepaid revenue × completion rate
A9: Year-end bonus rate | B9: =Assumptions!$B$12/100 | C9: Rep % of completed-contract value
A10: Year-end MSA-completion bonus | B10: =B8*B9 | C10: Completed value × bonus rate

Sheet Full Forecast P&L
A1: JHI Research & Analytics Firm, Inc.
A2: Full-year forecast P&L — all expenditures included
A3: generated 2026-07-30 · JHI-SIG: 69M2705M
A4: 1,200 prepaid annual subs (editable). Includes COGS + upfront 15% commission + year-end MSA bonus + all operating costs. Illustrative internal model.
A5: Revenue (prepaid annual, net) | B5: =Assumptions!$B$17
A6: Payment processing | B6: =-B5*Assumptions!$B$20/100
A7: Infrastructure & support | B7: =-B5*Assumptions!$B$21/100
A8: Data license (SF1) | B8: =-Assumptions!$B$22
A9: Gross profit | B9: =B5+SUM(B6:B8)
A10: Upfront sales commission (15%) | B10: =-'Upfront Commission (15%)'!$D$10
A11: Year-end MSA-completion bonus | B11: =-'Year-End MSA Bonus'!$B$10
A12: Marketing | B12: =-Assumptions!$B$23
A13: Legal & accounting | B13: =-Assumptions!$B$24
A14: Software & AI tools | B14: =-Assumptions!$B$25
A15: Founder / ops comp | B15: =-Assumptions!$B$26
A16: Total operating expenses | B16: =SUM(B10:B15)
A17: EBITDA | B17: =B9+B16
A18: EBITDA margin | B18: =IF(B5=0,0,B17/B5)
A19: Total salesperson compensation | B19: ='Upfront Commission (15%)'!$D$10+'Year-End MSA Bonus'!$B$10
A21: Reality check: 1,200 premium prepaid subs in Year 1 from one rep is an aggressive 'ceiling' scenario. Dial closes/mo down in Assumptions for a base case.

Sheet Monthly (Bookings)
A1: JHI Research & Analytics Firm, Inc.
A2: Monthly breakdown — bookings / cash basis
A3: generated 2026-07-30 · JHI-SIG: 69M2705M
A4: Each month books `closes` prepaid annual contracts: full annual value collected + 15% commission paid UP FRONT that month. Year-end MSA bonus in Mo 12. Sums to the P&L.
A5: $ per month | B5: Mo 1 | C5: Mo 2 | D5: Mo 3 | E5: Mo 4 | F5: Mo 5 | G5: Mo 6 | H5: Mo 7 | I5: Mo 8 | J5: Mo 9 | K5: Mo 10 | L5: Mo 11 | M5: Mo 12 | N5: Year 1
A6: New subscriptions | B6: =Assumptions!$B$8 | C6: =Assumptions!$B$8 | D6: =Assumptions!$B$8 | E6: =Assumptions!$B$8 | F6: =Assumptions!$B$8 | G6: =Assumptions!$B$8 | H6: =Assumptions!$B$8 | I6: =Assumptions!$B$8 | ... M6: =Assumptions!$B$8 | N6: =SUM(B6:M6)
A7: Revenue (booked) | B7: =Assumptions!$B$8*Assumptions!$B$16 | C7: =Assumptions!$B$8*Assumptions!$B$16 | D7: =Assumptions!$B$8*Assumptions!$B$16 | E7: =Assumptions!$B$8*Assumptions!$B$16 | F7: =Assumptions!$B$8*Assumptions!$B$16 | G7: =Assumptions!$B$8*Assumptions!$B$16 | H7: =Assumptions!$B$8*Assumptions!$B$16 | I7: =Assumptions!$B$8*Assumptions!$B$16 | ... M7: =Assumptions!$B$8*Assumptions!$B$16 | N7: =SUM(B7:M7)
A8: Payment processing | B8: =B7*Assumptions!$B$20/100 | C8: =C7*Assumptions!$B$20/100 | D8: =D7*Assumptions!$B$20/100 | E8: =E7*Assumptions!$B$20/100 | F8: =F7*Assumptions!$B$20/100 | G8: =G7*Assumptions!$B$20/100 | H8: =H7*Assumptions!$B$20/100 | I8: =I7*Assumptions!$B$20/100 | ... M8: =M7*Assumptions!$B$20/100 | N8: =SUM(B8:M8)
A9: Infrastructure & support | B9: =B7*Assumptions!$B$21/100 | C9: =C7*Assumptions!$B$21/100 | D9: =D7*Assumptions!$B$21/100 | E9: =E7*Assumptions!$B$21/100 | F9: =F7*Assumptions!$B$21/100 | G9: =G7*Assumptions!$B$21/100 | H9: =H7*Assumptions!$B$21/100 | I9: =I7*Assumptions!$B$21/100 | ... M9: =M7*Assumptions!$B$21/100 | N9: =SUM(B9:M9)
A10: Data license (SF1) | B10: =Assumptions!$B$22/12 | C10: =Assumptions!$B$22/12 | D10: =Assumptions!$B$22/12 | E10: =Assumptions!$B$22/12 | F10: =Assumptions!$B$22/12 | G10: =Assumptions!$B$22/12 | H10: =Assumptions!$B$22/12 | I10: =Assumptions!$B$22/12 | ... M10: =Assumptions!$B$22/12 | N10: =SUM(B10:M10)
A11: Total COGS | B11: =SUM(B8:B10) | C11: =SUM(C8:C10) | D11: =SUM(D8:D10) | E11: =SUM(E8:E10) | F11: =SUM(F8:F10) | G11: =SUM(G8:G10) | H11: =SUM(H8:H10) | I11: =SUM(I8:I10) | ... M11: =SUM(M8:M10) | N11: =SUM(B11:M11)
A12: Gross profit | B12: =B7-B11 | C12: =C7-C11 | D12: =D7-D11 | E12: =E7-E11 | F12: =F7-F11 | G12: =G7-G11 | H12: =H7-H11 | I12: =I7-I11 | ... M12: =M7-M11 | N12: =SUM(B12:M12)
A13: Upfront commission (15%) | B13: =B7*Assumptions!$B$10/100 | C13: =C7*Assumptions!$B$10/100 | D13: =D7*Assumptions!$B$10/100 | E13: =E7*Assumptions!$B$10/100 | F13: =F7*Assumptions!$B$10/100 | G13: =G7*Assumptions!$B$10/100 | H13: =H7*Assumptions!$B$10/100 | I13: =I7*Assumptions!$B$10/100 | ... M13: =M7*Assumptions!$B$10/100 | N13: =SUM(B13:M13)
A14: Year-end MSA bonus | B14: 0 | C14: 0 | D14: 0 | E14: 0 | F14: 0 | G14: 0 | H14: 0 | I14: 0 | J14: 0 | K14: 0 | L14: 0 | M14: =Assumptions!$B$17*Assumptions!$B$11/100*Assumptions!$B$12/100 | N14: =SUM(B14:M14)
A15: Fixed opex (mktg/legal/sw/founder) | B15: =(Assumptions!$B$23+Assumptions!$B$24+Assumptions!$B$25+Assumptions!$B$26)/12 | C15: =(Assumptions!$B$23+Assumptions!$B$24+Assumptions!$B$25+Assumptions!$B$26)/12 | D15: =(Assumptions!$B$23+Assumptions!$B$24+Assumptions!$B$25+Assumptions!$B$26)/12 | E15: =(Assumptions!$B$23+Assumptions!$B$24+Assumptions!$B$25+Assumptions!$B$26)/12 | F15: =(Assumptions!$B$23+Assumptions!$B$24+Assumptions!$B$25+Assumptions!$B$26)/12 | G15: =(Assumptions!$B$23+Assumptions!$B$24+Assumptions!$B$25+Assumptions!$B$26)/12 | H15: =(Assumptions!$B$23+Assumptions!$B$24+Assumptions!$B$25+Assumptions!$B$26)/12 | I15: =(Assumptions!$B$23+Assumptions!$B$24+Assumptions!$B$25+Assumptions!$B$26)/12 | ... M15: =(Assumptions!$B$23+Assumptions!$B$24+Assumptions!$B$25+Assumptions!$B$26)/12 | N15: =SUM(B15:M15)
A16: Total operating expenses | B16: =B13+B14+B15 | C16: =C13+C14+C15 | D16: =D13+D14+D15 | E16: =E13+E14+E15 | F16: =F13+F14+F15 | G16: =G13+G14+G15 | H16: =H13+H14+H15 | I16: =I13+I14+I15 | ... M16: =M13+M14+M15 | N16: =SUM(B16:M16)
A17: EBITDA | B17: =B12-B16 | C17: =C12-C16 | D17: =D12-D16 | E17: =E12-E16 | F17: =F12-F16 | G17: =G12-G16 | H17: =H12-H16 | I17: =I12-I16 | ... M17: =M12-M16 | N17: =SUM(B17:M17)
A18: EBITDA margin | B18: =IF(B7=0,0,B17/B7) | C18: =IF(C7=0,0,C17/C7) | D18: =IF(D7=0,0,D17/D7) | E18: =IF(E7=0,0,E17/E7) | F18: =IF(F7=0,0,F17/F7) | G18: =IF(G7=0,0,G17/G7) | H18: =IF(H7=0,0,H17/H7) | I18: =IF(I7=0,0,I17/I7) | ... N18: =IF(N7=0,0,N17/N7)

Sheet Monthly (Accrual)
A1: JHI Research & Analytics Firm, Inc.
A2: Monthly breakdown — accrual basis (ASC 606)
A3: generated 2026-07-30 · JHI-SIG: 69M2705M
A4: Revenue recognized ratably as cohorts stack; commission amortized over 12 mo. Builds monthly; the balance is deferred revenue carried to Yr 2 (see note).
A5: $ per month | B5: Mo 1 | C5: Mo 2 | D5: Mo 3 | E5: Mo 4 | F5: Mo 5 | G5: Mo 6 | H5: Mo 7 | I5: Mo 8 | J5: Mo 9 | K5: Mo 10 | L5: Mo 11 | M5: Mo 12 | N5: Year 1
A6: Recognized revenue | B6: =1*Assumptions!$B$8*Assumptions!$B$16/12 | C6: =2*Assumptions!$B$8*Assumptions!$B$16/12 | D6: =3*Assumptions!$B$8*Assumptions!$B$16/12 | E6: =4*Assumptions!$B$8*Assumptions!$B$16/12 | F6: =5*Assumptions!$B$8*Assumptions!$B$16/12 | G6: =6*Assumptions!$B$8*Assumptions!$B$16/12 | H6: =7*Assumptions!$B$8*Assumptions!$B$16/12 | I6: =8*Assumptions!$B$8*Assumptions!$B$16/12 | J6: =9*Assumptions!$B$8*Assumptions!$B$16/12 | K6: =10*Assumptions!$B$8*Assumptions!$B$16/12 | L6: =11*Assumptions!$B$8*Assumptions!$B$16/12 | M6: =12*Assumptions!$B$8*Assumptions!$B$16/12 | N6: =SUM(B6:M6)
A7: Total COGS | B7: =B6*(Assumptions!$B$20+Assumptions!$B$21)/100+Assumptions!$B$22/12 | C7: =C6*(Assumptions!$B$20+Assumptions!$B$21)/100+Assumptions!$B$22/12 | D7: =D6*(Assumptions!$B$20+Assumptions!$B$21)/100+Assumptions!$B$22/12 | E7: =E6*(Assumptions!$B$20+Assumptions!$B$21)/100+Assumptions!$B$22/12 | F7: =F6*(Assumptions!$B$20+Assumptions!$B$21)/100+Assumptions!$B$22/12 | G7: =G6*(Assumptions!$B$20+Assumptions!$B$21)/100+Assumptions!$B$22/12 | H7: =H6*(Assumptions!$B$20+Assumptions!$B$21)/100+Assumptions!$B$22/12 | I7: =I6*(Assumptions!$B$20+Assumptions!$B$21)/100+Assumptions!$B$22/12 | ... M7: =M6*(Assumptions!$B$20+Assumptions!$B$21)/100+Assumptions!$B$22/12 | N7: =SUM(B7:M7)
A8: Gross profit | B8: =B6-B7 | C8: =C6-C7 | D8: =D6-D7 | E8: =E6-E7 | F8: =F6-F7 | G8: =G6-G7 | H8: =H6-H7 | I8: =I6-I7 | ... M8: =M6-M7 | N8: =SUM(B8:M8)
A9: Commission (amortized) | B9: =1*(Assumptions!$B$8*Assumptions!$B$16*Assumptions!$B$10/100)/12 | C9: =2*(Assumptions!$B$8*Assumptions!$B$16*Assumptions!$B$10/100)/12 | D9: =3*(Assumptions!$B$8*Assumptions!$B$16*Assumptions!$B$10/100)/12 | E9: =4*(Assumptions!$B$8*Assumptions!$B$16*Assumptions!$B$10/100)/12 | F9: =5*(Assumptions!$B$8*Assumptions!$B$16*Assumptions!$B$10/100)/12 | G9: =6*(Assumptions!$B$8*Assumptions!$B$16*Assumptions!$B$10/100)/12 | H9: =7*(Assumptions!$B$8*Assumptions!$B$16*Assumptions!$B$10/100)/12 | I9: =8*(Assumptions!$B$8*Assumptions!$B$16*Assumptions!$B$10/100)/12 | J9: =9*(Assumptions!$B$8*Assumptions!$B$16*Assumptions!$B$10/100)/12 | K9: =10*(Assumptions!$B$8*Assumptions!$B$16*Assumptions!$B$10/100)/12 | L9: =11*(Assumptions!$B$8*Assumptions!$B$16*Assumptions!$B$10/100)/12 | M9: =12*(Assumptions!$B$8*Assumptions!$B$16*Assumptions!$B$10/100)/12 | N9: =SUM(B9:M9)
A10: Fixed opex | B10: =(Assumptions!$B$23+Assumptions!$B$24+Assumptions!$B$25+Assumptions!$B$26)/12 | C10: =(Assumptions!$B$23+Assumptions!$B$24+Assumptions!$B$25+Assumptions!$B$26)/12 | D10: =(Assumptions!$B$23+Assumptions!$B$24+Assumptions!$B$25+Assumptions!$B$26)/12 | E10: =(Assumptions!$B$23+Assumptions!$B$24+Assumptions!$B$25+Assumptions!$B$26)/12 | F10: =(Assumptions!$B$23+Assumptions!$B$24+Assumptions!$B$25+Assumptions!$B$26)/12 | G10: =(Assumptions!$B$23+Assumptions!$B$24+Assumptions!$B$25+Assumptions!$B$26)/12 | H10: =(Assumptions!$B$23+Assumptions!$B$24+Assumptions!$B$25+Assumptions!$B$26)/12 | I10: =(Assumptions!$B$23+Assumptions!$B$24+Assumptions!$B$25+Assumptions!$B$26)/12 | ... M10: =(Assumptions!$B$23+Assumptions!$B$24+Assumptions!$B$25+Assumptions!$B$26)/12 | N10: =SUM(B10:M10)
A11: Year-end MSA bonus | B11: 0 | C11: 0 | D11: 0 | E11: 0 | F11: 0 | G11: 0 | H11: 0 | I11: 0 | J11: 0 | K11: 0 | L11: 0 | M11: =Assumptions!$B$8*Assumptions!$B$11/100*Assumptions!$B$16*Assumptions!$B$12/100 | N11: =SUM(B11:M11)
A12: EBITDA | B12: =B8-B9-B10-B11 | C12: =C8-C9-C10-C11 | D12: =D8-D9-D10-D11 | E12: =E8-E9-E10-E11 | F12: =F8-F9-F10-F11 | G12: =G8-G9-G10-G11 | H12: =H8-H9-H10-H11 | I12: =I8-I9-I10-I11 | ... M12: =M8-M9-M10-M11 | N12: =SUM(B12:M12)
A13: EBITDA margin | B13: =IF(B6=0,0,B12/B6) | C13: =IF(C6=0,0,C12/C6) | D13: =IF(D6=0,0,D12/D6) | E13: =IF(E6=0,0,E12/E6) | F13: =IF(F6=0,0,F12/F6) | G13: =IF(G6=0,0,G12/G6) | H13: =IF(H6=0,0,H12/H6) | I13: =IF(I6=0,0,I12/I6) | ... N13: =IF(N6=0,0,N12/N6)
A15: Deferred to Yr 2 (booked − recognized): | N15: =Assumptions!$B$17-N6
A16: Note: booked cash = full annual up front (see Bookings tab); accrual recognizes ratably, so Yr-1 EBITDA is lower but Yr 2 opens with revenue in hand.

Sheet Salesperson Total Comp
A1: JHI Research & Analytics Firm, Inc.
A2: Salesperson total compensation & mix sensitivity
A3: generated 2026-07-30 · JHI-SIG: 69M2705M
A5: Upfront commission (15%) | B5: ='Upfront Commission (15%)'!$D$10
A6: Year-end MSA-completion bonus | B6: ='Year-End MSA Bonus'!$B$10
A7: Total salesperson compensation | B7: =B5+B6
A8: Total comp as % of revenue | B8: =IF(Assumptions!$B$17=0,0,B7/Assumptions!$B$17)
A11: Sensitivity — by Tier-1 mix (1,200 subs)
A12: Metric | B12: 0% T1 | C12: 10% T1 | D12: 20% T1
A13: Avg full-paid price / sub (net) | B13: =((Assumptions!$B$5*0/100)+(Assumptions!$B$6*(1-0/100)))*12*(1-Assumptions!$B$9/100) | C13: =((Assumptions!$B$5*10/100)+(Assumptions!$B$6*(1-10/100)))*12*(1-Assumptions!$B$9/100) | D13: =((Assumptions!$B$5*20/100)+(Assumptions!$B$6*(1-20/100)))*12*(1-Assumptions!$B$9/100)
A14: Prepaid annual revenue (net) | B14: =Assumptions!$B$15*((Assumptions!$B$5*0/100)+(Assumptions!$B$6*(1-0/100)))*12*(1-Assumptions!$B$9/100) | C14: =Assumptions!$B$15*((Assumptions!$B$5*10/100)+(Assumptions!$B$6*(1-10/100)))*12*(1-Assumptions!$B$9/100) | D14: =Assumptions!$B$15*((Assumptions!$B$5*20/100)+(Assumptions!$B$6*(1-20/100)))*12*(1-Assumptions!$B$9/100)
A15: Upfront commission (15%) | B15: =(Assumptions!$B$15*((Assumptions!$B$5*0/100)+(Assumptions!$B$6*(1-0/100)))*12*(1-Assumptions!$B$9/100))*Assumptions!$B$10/100 | C15: =(Assumptions!$B$15*((Assumptions!$B$5*10/100)+(Assumptions!$B$6*(1-10/100)))*12*(1-Assumptions!$B$9/100))*Assumptions!$B$10/100 | D15: =(Assumptions!$B$15*((Assumptions!$B$5*20/100)+(Assumptions!$B$6*(1-20/100)))*12*(1-Assumptions!$B$9/100))*Assumptions!$B$10/100
A16: Year-end MSA bonus | B16: =(Assumptions!$B$15*((Assumptions!$B$5*0/100)+(Assumptions!$B$6*(1-0/100)))*12*(1-Assumptions!$B$9/100))*Assumptions!$B$11/100*Assumptions!$B$12/100 | C16: =(Assumptions!$B$15*((Assumptions!$B$5*10/100)+(Assumptions!$B$6*(1-10/100)))*12*(1-Assumptions!$B$9/100))*Assumptions!$B$11/100*Assumptions!$B$12/100 | D16: =(Assumptions!$B$15*((Assumptions!$B$5*20/100)+(Assumptions!$B$6*(1-20/100)))*12*(1-Assumptions!$B$9/100))*Assumptions!$B$11/100*Assumptions!$B$12/100
A17: Total salesperson comp | B17: =B15+B16 | C17: =C15+C16 | D17: =D15+D16
A19: Note: upfront commission is front-loaded cash at signing; the year-end bonus rewards 12-mo MSA completion (retention). Confirm plan mechanics with counsel/CPA.

Sheet Legal & Provenance
A1: JHI Research & Analytics Firm, Inc.
A3: Internal planning model from user-supplied assumptions — illustrative only, not a forecast, offer of employment, or compensation guarantee.
A4: Upfront commission is paid on collected, full-paid (prepaid annual) contracts. Consider a pro-rata clawback if a prepaid contract is refunded/cancelled before the 12-mo MSA completes.
A5: The year-end MSA-completion bonus rewards contracts that complete the full 12-month term.
A6: Founder signature of provenance: JHI-SIG: 69M2705M
A7: © 2026 JHI Research & Analytics Firm, Inc.. All rights reserved. Confidential.
