Workbook

Sheet Assumptions
A1: JHI Research & Analytics Firm, Inc.
A2: Prepaid-MSA Sales Commission — assumptions
A3: generated 2026-07-18 · JHI-SIG: 69M2705M
A5: Tier 1 price ($/mo) | B5: 1500 | C5: Enterprise / Family Office
A6: Tier 2 price ($/mo) | B6: 299 | C6: Professional
A7: Tier 1 mix (% of closes) | B7: 10 | C7: Share of closes that are Tier 1
A8: Closes per month | B8: 100 | C8: New full-paid subs signed each month
A9: Annual prepay discount (%) | B9: 10 | C9: Discount for paying 12 months up front
A10: Upfront commission rate (%) | B10: 15 | C10: Rep % of full-paid (net) contract value, at signing
A11: MSA completion / renewal rate (%) | B11: 90 | C11: Share of contracts that complete the full 12-mo MSA
A12: Year-end MSA-completion bonus rate (%) | B12: 5 | C12: Rep bonus % of completed-contract value, paid at year-end
A14: DERIVED
A15: Subscriptions per year | B15: =B8*12 | C15: Closes/mo × 12 (e.g. 100 → 1,200)
A16: Avg full-paid price / sub (net, annual) | B16: =((B5*B7/100)+(B6*(1-B7/100)))*12*(1-B9/100) | C16: Blended monthly price × 12 × (1 − prepay discount)
A17: Total prepaid annual revenue (net) | B17: =B15*B16
A19: OPERATING ASSUMPTIONS (editable)
A20: Payment processing (% of revenue) | B20: 3
A21: Infra / support (% of revenue) | B21: 2
A22: Data license — SF1 ($/yr, fixed) | B22: 18000
A23: Marketing ($/yr) | B23: 36000
A24: Legal & accounting ($/yr) | B24: 18000
A25: Software & AI tools ($/yr) | B25: 12000
A26: Founder / ops comp ($/yr) | B26: 60000

Sheet Upfront Commission (15%)
A1: JHI Research & Analytics Firm, Inc.
A2: Upfront commission — 15% of full-paid (net) contract value
A3: generated 2026-07-18 · JHI-SIG: 69M2705M
A4: Contracts are prepaid annual (12-mo MSA). Rep earns the upfront commission at signing on the net (post-discount) contract value. Pay on collected cash.
B5: Tier 1 | C5: Tier 2 | D5: Total
A6: Subscriptions / year | B6: =Assumptions!$B$15*Assumptions!$B$7/100 | C6: =Assumptions!$B$15*(1-Assumptions!$B$7/100) | D6: =B6+C6
A7: Full-paid price / sub (net, annual) | B7: =Assumptions!$B$5*12*(1-Assumptions!$B$9/100) | C7: =Assumptions!$B$6*12*(1-Assumptions!$B$9/100)
A8: Prepaid annual revenue (net) | B8: =B6*B7 | C8: =C6*C7 | D8: =B8+C8
A9: Upfront commission / sub (15%) | B9: =B7*Assumptions!$B$10/100 | C9: =C7*Assumptions!$B$10/100
A10: Upfront commission (total) | B10: =B8*Assumptions!$B$10/100 | C10: =C8*Assumptions!$B$10/100 | D10: =B10+C10
A13: Cash-flow note: 15% paid UP FRONT on the full annual contract is front-loaded vs. a monthly residual — model the cash outlay at signing.

Sheet Year-End MSA Bonus
A1: JHI Research & Analytics Firm, Inc.
A2: Year-end MSA-completion bonus
A3: generated 2026-07-18 · JHI-SIG: 69M2705M
A4: Additional bonus rewarding contracts that COMPLETE the full 12-month MSA term (retention). Paid at year-end on completed-contract value.
A5: Subscriptions / year (signed) | B5: =Assumptions!$B$15 | C5: From Assumptions (closes/mo × 12)
A6: MSA completion / renewal rate | B6: =Assumptions!$B$11/100 | C6: Share completing the full 12-mo term
A7: Contracts completing full 12-mo MSA | B7: =B5*B6 | C7: Signed × completion rate
A8: Completed-contract value (net) | B8: =Assumptions!$B$17*B6 | C8: Total prepaid revenue × completion rate
A9: Year-end bonus rate | B9: =Assumptions!$B$12/100 | C9: Rep % of completed-contract value
A10: Year-end MSA-completion bonus | B10: =B8*B9 | C10: Completed value × bonus rate

Sheet Full Forecast P&L
A1: JHI Research & Analytics Firm, Inc.
A2: Full-year forecast P&L — all expenditures included
A3: generated 2026-07-18 · JHI-SIG: 69M2705M
A4: 1,200 prepaid annual subs (editable). Includes COGS + upfront 15% commission + year-end MSA bonus + all operating costs. Illustrative internal model.
A5: Revenue (prepaid annual, net) | B5: =Assumptions!$B$17
A6: Payment processing | B6: =-B5*Assumptions!$B$20/100
A7: Infrastructure & support | B7: =-B5*Assumptions!$B$21/100
A8: Data license (SF1) | B8: =-Assumptions!$B$22
A9: Gross profit | B9: =B5+SUM(B6:B8)
A10: Upfront sales commission (15%) | B10: =-'Upfront Commission (15%)'!$D$10
A11: Year-end MSA-completion bonus | B11: =-'Year-End MSA Bonus'!$B$10
A12: Marketing | B12: =-Assumptions!$B$23
A13: Legal & accounting | B13: =-Assumptions!$B$24
A14: Software & AI tools | B14: =-Assumptions!$B$25
A15: Founder / ops comp | B15: =-Assumptions!$B$26
A16: Total operating expenses | B16: =SUM(B10:B15)
A17: EBITDA | B17: =B9+B16
A18: EBITDA margin | B18: =IF(B5=0,0,B17/B5)
A19: Total salesperson compensation | B19: ='Upfront Commission (15%)'!$D$10+'Year-End MSA Bonus'!$B$10
A21: Reality check: 1,200 premium prepaid subs in Year 1 from one rep is an aggressive 'ceiling' scenario. Dial closes/mo down in Assumptions for a base case.

Sheet Salesperson Total Comp
A1: JHI Research & Analytics Firm, Inc.
A2: Salesperson total compensation & mix sensitivity
A3: generated 2026-07-18 · JHI-SIG: 69M2705M
A5: Upfront commission (15%) | B5: ='Upfront Commission (15%)'!$D$10
A6: Year-end MSA-completion bonus | B6: ='Year-End MSA Bonus'!$B$10
A7: Total salesperson compensation | B7: =B5+B6
A8: Total comp as % of revenue | B8: =IF(Assumptions!$B$17=0,0,B7/Assumptions!$B$17)
A11: Sensitivity — by Tier-1 mix (1,200 subs)
A12: Metric | B12: 0% T1 | C12: 10% T1 | D12: 20% T1
A13: Avg full-paid price / sub (net) | B13: =((Assumptions!$B$5*0/100)+(Assumptions!$B$6*(1-0/100)))*12*(1-Assumptions!$B$9/100) | C13: =((Assumptions!$B$5*10/100)+(Assumptions!$B$6*(1-10/100)))*12*(1-Assumptions!$B$9/100) | D13: =((Assumptions!$B$5*20/100)+(Assumptions!$B$6*(1-20/100)))*12*(1-Assumptions!$B$9/100)
A14: Prepaid annual revenue (net) | B14: =Assumptions!$B$15*((Assumptions!$B$5*0/100)+(Assumptions!$B$6*(1-0/100)))*12*(1-Assumptions!$B$9/100) | C14: =Assumptions!$B$15*((Assumptions!$B$5*10/100)+(Assumptions!$B$6*(1-10/100)))*12*(1-Assumptions!$B$9/100) | D14: =Assumptions!$B$15*((Assumptions!$B$5*20/100)+(Assumptions!$B$6*(1-20/100)))*12*(1-Assumptions!$B$9/100)
A15: Upfront commission (15%) | B15: =(Assumptions!$B$15*((Assumptions!$B$5*0/100)+(Assumptions!$B$6*(1-0/100)))*12*(1-Assumptions!$B$9/100))*Assumptions!$B$10/100 | C15: =(Assumptions!$B$15*((Assumptions!$B$5*10/100)+(Assumptions!$B$6*(1-10/100)))*12*(1-Assumptions!$B$9/100))*Assumptions!$B$10/100 | D15: =(Assumptions!$B$15*((Assumptions!$B$5*20/100)+(Assumptions!$B$6*(1-20/100)))*12*(1-Assumptions!$B$9/100))*Assumptions!$B$10/100
A16: Year-end MSA bonus | B16: =(Assumptions!$B$15*((Assumptions!$B$5*0/100)+(Assumptions!$B$6*(1-0/100)))*12*(1-Assumptions!$B$9/100))*Assumptions!$B$11/100*Assumptions!$B$12/100 | C16: =(Assumptions!$B$15*((Assumptions!$B$5*10/100)+(Assumptions!$B$6*(1-10/100)))*12*(1-Assumptions!$B$9/100))*Assumptions!$B$11/100*Assumptions!$B$12/100 | D16: =(Assumptions!$B$15*((Assumptions!$B$5*20/100)+(Assumptions!$B$6*(1-20/100)))*12*(1-Assumptions!$B$9/100))*Assumptions!$B$11/100*Assumptions!$B$12/100
A17: Total salesperson comp | B17: =B15+B16 | C17: =C15+C16 | D17: =D15+D16
A19: Note: upfront commission is front-loaded cash at signing; the year-end bonus rewards 12-mo MSA completion (retention). Confirm plan mechanics with counsel/CPA.

Sheet Legal & Provenance
A1: JHI Research & Analytics Firm, Inc.
A3: Internal planning model from user-supplied assumptions — illustrative only, not a forecast, offer of employment, or compensation guarantee.
A4: Upfront commission is paid on collected, full-paid (prepaid annual) contracts. Consider a pro-rata clawback if a prepaid contract is refunded/cancelled before the 12-mo MSA completes.
A5: The year-end MSA-completion bonus rewards contracts that complete the full 12-month term.
A6: Founder signature of provenance: JHI-SIG: 69M2705M
A7: © 2026 JHI Research & Analytics Firm, Inc.. All rights reserved. Confidential.
