Workbook

Sheet Assumptions
A1: JHI Research & Analytics Firm, Inc.
A2: Sales Commission Model — assumptions
A3: generated 2026-07-12 · JHI-SIG: 69M2705M
A5: Tier 1 price ($/mo) | B5: 1500 | C5: Enterprise / Family Office
A6: Tier 2 price ($/mo) | B6: 299 | C6: Professional
A7: Tier 1 mix (% of closes) | B7: 0 | C7: 0 = all Tier 2; try 10 or 20
A8: Closes per month | B8: 100 | C8: New subs signed each month
A9: Residual commission (% of MRR) | B9: 10 | C9: Paid monthly while active
A10: Monthly churn (%) | B10: 0 | C10: Subs lost per month
A11: Blended gross margin (%) | B11: 96 | C11: For JHI contribution
A13: Avg MRR / sub | B13: =$B$5*$B$7/100+$B$6*(1-$B$7/100)
A15: OPERATING ASSUMPTIONS (editable)
A16: Payment processing (% of revenue) | B16: 3
A17: Infra / support (% of revenue) | B17: 2
A18: Data license — SF1 ($/yr, fixed) | B18: 18000
A19: Marketing ($/yr) | B19: 36000
A20: Legal & accounting ($/yr) | B20: 18000
A21: Software & AI tools ($/yr) | B21: 12000
A22: Founder / ops comp ($/yr) | B22: 60000

Sheet Monthly Model
A1: JHI Research & Analytics Firm, Inc.
A2: 24-month commission schedule (live)
A3: generated 2026-07-12 · JHI-SIG: 69M2705M
A5: Month | B5: New subs | C5: Active subs | D5: Avg MRR | E5: Billed MRR | F5: Commission | G5: JHI GM after comm.
A6: 1 | B6: =Assumptions!$B$8 | C6: =B6 | D6: =Assumptions!$B$13 | E6: =C6*D6 | F6: =E6*Assumptions!$B$9/100 | G6: =E6*Assumptions!$B$11/100-F6
A7: 2 | B7: =Assumptions!$B$8 | C7: =C6*(1-Assumptions!$B$10/100)+B7 | D7: =Assumptions!$B$13 | E7: =C7*D7 | F7: =E7*Assumptions!$B$9/100 | G7: =E7*Assumptions!$B$11/100-F7
A8: 3 | B8: =Assumptions!$B$8 | C8: =C7*(1-Assumptions!$B$10/100)+B8 | D8: =Assumptions!$B$13 | E8: =C8*D8 | F8: =E8*Assumptions!$B$9/100 | G8: =E8*Assumptions!$B$11/100-F8
A9: 4 | B9: =Assumptions!$B$8 | C9: =C8*(1-Assumptions!$B$10/100)+B9 | D9: =Assumptions!$B$13 | E9: =C9*D9 | F9: =E9*Assumptions!$B$9/100 | G9: =E9*Assumptions!$B$11/100-F9
A10: 5 | B10: =Assumptions!$B$8 | C10: =C9*(1-Assumptions!$B$10/100)+B10 | D10: =Assumptions!$B$13 | E10: =C10*D10 | F10: =E10*Assumptions!$B$9/100 | G10: =E10*Assumptions!$B$11/100-F10
A11: 6 | B11: =Assumptions!$B$8 | C11: =C10*(1-Assumptions!$B$10/100)+B11 | D11: =Assumptions!$B$13 | E11: =C11*D11 | F11: =E11*Assumptions!$B$9/100 | G11: =E11*Assumptions!$B$11/100-F11
A12: 7 | B12: =Assumptions!$B$8 | C12: =C11*(1-Assumptions!$B$10/100)+B12 | D12: =Assumptions!$B$13 | E12: =C12*D12 | F12: =E12*Assumptions!$B$9/100 | G12: =E12*Assumptions!$B$11/100-F12
A13: 8 | B13: =Assumptions!$B$8 | C13: =C12*(1-Assumptions!$B$10/100)+B13 | D13: =Assumptions!$B$13 | E13: =C13*D13 | F13: =E13*Assumptions!$B$9/100 | G13: =E13*Assumptions!$B$11/100-F13
A14: 9 | B14: =Assumptions!$B$8 | C14: =C13*(1-Assumptions!$B$10/100)+B14 | D14: =Assumptions!$B$13 | E14: =C14*D14 | F14: =E14*Assumptions!$B$9/100 | G14: =E14*Assumptions!$B$11/100-F14
A15: 10 | B15: =Assumptions!$B$8 | C15: =C14*(1-Assumptions!$B$10/100)+B15 | D15: =Assumptions!$B$13 | E15: =C15*D15 | F15: =E15*Assumptions!$B$9/100 | G15: =E15*Assumptions!$B$11/100-F15
A16: 11 | B16: =Assumptions!$B$8 | C16: =C15*(1-Assumptions!$B$10/100)+B16 | D16: =Assumptions!$B$13 | E16: =C16*D16 | F16: =E16*Assumptions!$B$9/100 | G16: =E16*Assumptions!$B$11/100-F16
A17: 12 | B17: =Assumptions!$B$8 | C17: =C16*(1-Assumptions!$B$10/100)+B17 | D17: =Assumptions!$B$13 | E17: =C17*D17 | F17: =E17*Assumptions!$B$9/100 | G17: =E17*Assumptions!$B$11/100-F17
A18: 13 | B18: =Assumptions!$B$8 | C18: =C17*(1-Assumptions!$B$10/100)+B18 | D18: =Assumptions!$B$13 | E18: =C18*D18 | F18: =E18*Assumptions!$B$9/100 | G18: =E18*Assumptions!$B$11/100-F18
... A29: 24 | B29: =Assumptions!$B$8 | C29: =C28*(1-Assumptions!$B$10/100)+B29 | D29: =Assumptions!$B$13 | E29: =C29*D29 | F29: =E29*Assumptions!$B$9/100 | G29: =E29*Assumptions!$B$11/100-F29
A31: Year-1 commission | F31: =SUM(F6:F17)
A32: Year-2 commission | F32: =SUM(F18:F29)
A33: Exit run-rate (mo 12 × 12) | F33: =F17*12
A34: Year-1 JHI GM after commission | G34: =SUM(G6:G17)

Sheet Year-1 by Mix
A1: JHI Research & Analytics Firm, Inc.
A2: Year-1 commission by Tier 1 / Tier 2 mix
A3: generated 2026-07-12 · JHI-SIG: 69M2705M
A5: Ramp basis: 100 closes/mo → sub-months = closes × (1+2+…+12) = closes × 78 (no churn).
A7: Mix (T1 / T2) | B7: Avg MRR | C7: Year-1 commission | D7: Exit run-rate (yr)
A8: 0% / 100% | B8: =Assumptions!$B$5*0/100+Assumptions!$B$6*(1-0/100) | C8: =Assumptions!$B$9/100*B8*Assumptions!$B$8*78 | D8: =Assumptions!$B$8*12*B8*Assumptions!$B$9/100*12
A9: 10% / 90% | B9: =Assumptions!$B$5*10/100+Assumptions!$B$6*(1-10/100) | C9: =Assumptions!$B$9/100*B9*Assumptions!$B$8*78 | D9: =Assumptions!$B$8*12*B9*Assumptions!$B$9/100*12
A10: 20% / 80% | B10: =Assumptions!$B$5*20/100+Assumptions!$B$6*(1-20/100) | C10: =Assumptions!$B$9/100*B10*Assumptions!$B$8*78 | D10: =Assumptions!$B$8*12*B10*Assumptions!$B$9/100*12
A12: ~All-Tier-2 Year-1 ≈ $233K (a light Tier-1 sprinkle → ~$236K).

Sheet Year-1 EBITDA by Mix
A1: JHI Research & Analytics Firm, Inc.
A2: Year-1 EBITDA by Tier 1 / Tier 2 mix
A3: generated 2026-07-12 · JHI-SIG: 69M2705M
A5: Same 100/mo ramp (7,800 sub-months). Aggressive 'ceiling' scenario — see notes.
A6: Tier-1 mix % | B6: 0 | C6: 10 | D6: 20
A7: Avg MRR / sub | B7: =Assumptions!$B$5*B6/100+Assumptions!$B$6*(1-B6/100) | C7: =Assumptions!$B$5*C6/100+Assumptions!$B$6*(1-C6/100) | D7: =Assumptions!$B$5*D6/100+Assumptions!$B$6*(1-D6/100)
A8: Revenue (Year-1) | B8: =B7*Assumptions!$B$8*78 | C8: =C7*Assumptions!$B$8*78 | D8: =D7*Assumptions!$B$8*78
A9: COGS (proc+infra % + SF1) | B9: =B8*(Assumptions!$B$16+Assumptions!$B$17)/100+Assumptions!$B$18 | C9: =C8*(Assumptions!$B$16+Assumptions!$B$17)/100+Assumptions!$B$18 | D9: =D8*(Assumptions!$B$16+Assumptions!$B$17)/100+Assumptions!$B$18
A10: Gross profit | B10: =B8-B9 | C10: =C8-C9 | D10: =D8-D9
A11: Sales commission (residual) | B11: =B8*Assumptions!$B$9/100 | C11: =C8*Assumptions!$B$9/100 | D11: =D8*Assumptions!$B$9/100
A12: Marketing | B12: =Assumptions!$B$19 | C12: =Assumptions!$B$19 | D12: =Assumptions!$B$19
A13: Legal & accounting | B13: =Assumptions!$B$20 | C13: =Assumptions!$B$20 | D13: =Assumptions!$B$20
A14: Software & AI tools | B14: =Assumptions!$B$21 | C14: =Assumptions!$B$21 | D14: =Assumptions!$B$21
A15: Founder / ops comp | B15: =Assumptions!$B$22 | C15: =Assumptions!$B$22 | D15: =Assumptions!$B$22
A16: Total operating expenses | B16: =SUM(B11:B15) | C16: =SUM(C11:C15) | D16: =SUM(D11:D15)
A17: EBITDA | B17: =B10-B16 | C17: =C10-C16 | D17: =D10-D16
A18: EBITDA margin | B18: =IF(B8=0,0,B17/B8) | C18: =IF(C8=0,0,C17/C8) | D18: =IF(D8=0,0,D17/D8)

Sheet Monthly EBITDA & Opex
A1: JHI Research & Analytics Firm, Inc.
A2: Year-1 monthly EBITDA & operating-cost statement
A3: generated 2026-07-12 · JHI-SIG: 69M2705M
A4: Fixed annual costs spread /12; variable costs scale with revenue. Ramp = closes/mo from Assumptions; churn per Assumptions.
A5: $ per month | B5: Mo 1 | C5: Mo 2 | D5: Mo 3 | E5: Mo 4 | F5: Mo 5 | G5: Mo 6 | H5: Mo 7 | I5: Mo 8 | J5: Mo 9 | K5: Mo 10 | L5: Mo 11 | M5: Mo 12 | N5: Year 1
A6: New subscriptions | B6: =Assumptions!$B$8 | C6: =Assumptions!$B$8 | D6: =Assumptions!$B$8 | E6: =Assumptions!$B$8 | F6: =Assumptions!$B$8 | G6: =Assumptions!$B$8 | H6: =Assumptions!$B$8 | I6: =Assumptions!$B$8 | ... M6: =Assumptions!$B$8 | N6: =SUM(B6:M6)
A7: Active subscriptions | B7: =B6 | C7: =B7*(1-Assumptions!$B$10/100)+C6 | D7: =C7*(1-Assumptions!$B$10/100)+D6 | E7: =D7*(1-Assumptions!$B$10/100)+E6 | F7: =E7*(1-Assumptions!$B$10/100)+F6 | G7: =F7*(1-Assumptions!$B$10/100)+G6 | H7: =G7*(1-Assumptions!$B$10/100)+H6 | I7: =H7*(1-Assumptions!$B$10/100)+I6 | J7: =I7*(1-Assumptions!$B$10/100)+J6 | ... M7: =L7*(1-Assumptions!$B$10/100)+M6 | N7: =M7
A8: Billed MRR (revenue) | B8: =B7*Assumptions!$B$13 | C8: =C7*Assumptions!$B$13 | D8: =D7*Assumptions!$B$13 | E8: =E7*Assumptions!$B$13 | F8: =F7*Assumptions!$B$13 | G8: =G7*Assumptions!$B$13 | H8: =H7*Assumptions!$B$13 | I8: =I7*Assumptions!$B$13 | ... M8: =M7*Assumptions!$B$13 | N8: =SUM(B8:M8)
A9: Payment processing | B9: =B8*Assumptions!$B$16/100 | C9: =C8*Assumptions!$B$16/100 | D9: =D8*Assumptions!$B$16/100 | E9: =E8*Assumptions!$B$16/100 | F9: =F8*Assumptions!$B$16/100 | G9: =G8*Assumptions!$B$16/100 | H9: =H8*Assumptions!$B$16/100 | I9: =I8*Assumptions!$B$16/100 | ... M9: =M8*Assumptions!$B$16/100 | N9: =SUM(B9:M9)
A10: Infrastructure & support | B10: =B8*Assumptions!$B$17/100 | C10: =C8*Assumptions!$B$17/100 | D10: =D8*Assumptions!$B$17/100 | E10: =E8*Assumptions!$B$17/100 | F10: =F8*Assumptions!$B$17/100 | G10: =G8*Assumptions!$B$17/100 | H10: =H8*Assumptions!$B$17/100 | I10: =I8*Assumptions!$B$17/100 | ... M10: =M8*Assumptions!$B$17/100 | N10: =SUM(B10:M10)
A11: Data license (SF1) | B11: =Assumptions!$B$18/12 | C11: =Assumptions!$B$18/12 | D11: =Assumptions!$B$18/12 | E11: =Assumptions!$B$18/12 | F11: =Assumptions!$B$18/12 | G11: =Assumptions!$B$18/12 | H11: =Assumptions!$B$18/12 | I11: =Assumptions!$B$18/12 | ... M11: =Assumptions!$B$18/12 | N11: =SUM(B11:M11)
A12: Total COGS | B12: =SUM(B9:B11) | C12: =SUM(C9:C11) | D12: =SUM(D9:D11) | E12: =SUM(E9:E11) | F12: =SUM(F9:F11) | G12: =SUM(G9:G11) | H12: =SUM(H9:H11) | I12: =SUM(I9:I11) | ... M12: =SUM(M9:M11) | N12: =SUM(B12:M12)
A13: Gross profit | B13: =B8-B12 | C13: =C8-C12 | D13: =D8-D12 | E13: =E8-E12 | F13: =F8-F12 | G13: =G8-G12 | H13: =H8-H12 | I13: =I8-I12 | ... M13: =M8-M12 | N13: =SUM(B13:M13)
A14: Sales commission (residual) | B14: =B8*Assumptions!$B$9/100 | C14: =C8*Assumptions!$B$9/100 | D14: =D8*Assumptions!$B$9/100 | E14: =E8*Assumptions!$B$9/100 | F14: =F8*Assumptions!$B$9/100 | G14: =G8*Assumptions!$B$9/100 | H14: =H8*Assumptions!$B$9/100 | I14: =I8*Assumptions!$B$9/100 | ... M14: =M8*Assumptions!$B$9/100 | N14: =SUM(B14:M14)
A15: Marketing | B15: =Assumptions!$B$19/12 | C15: =Assumptions!$B$19/12 | D15: =Assumptions!$B$19/12 | E15: =Assumptions!$B$19/12 | F15: =Assumptions!$B$19/12 | G15: =Assumptions!$B$19/12 | H15: =Assumptions!$B$19/12 | I15: =Assumptions!$B$19/12 | ... M15: =Assumptions!$B$19/12 | N15: =SUM(B15:M15)
A16: Legal & accounting | B16: =Assumptions!$B$20/12 | C16: =Assumptions!$B$20/12 | D16: =Assumptions!$B$20/12 | E16: =Assumptions!$B$20/12 | F16: =Assumptions!$B$20/12 | G16: =Assumptions!$B$20/12 | H16: =Assumptions!$B$20/12 | I16: =Assumptions!$B$20/12 | ... M16: =Assumptions!$B$20/12 | N16: =SUM(B16:M16)
A17: Software & AI tools | B17: =Assumptions!$B$21/12 | C17: =Assumptions!$B$21/12 | D17: =Assumptions!$B$21/12 | E17: =Assumptions!$B$21/12 | F17: =Assumptions!$B$21/12 | G17: =Assumptions!$B$21/12 | H17: =Assumptions!$B$21/12 | I17: =Assumptions!$B$21/12 | ... M17: =Assumptions!$B$21/12 | N17: =SUM(B17:M17)
A18: Founder / ops comp | B18: =Assumptions!$B$22/12 | C18: =Assumptions!$B$22/12 | D18: =Assumptions!$B$22/12 | E18: =Assumptions!$B$22/12 | F18: =Assumptions!$B$22/12 | G18: =Assumptions!$B$22/12 | H18: =Assumptions!$B$22/12 | I18: =Assumptions!$B$22/12 | ... M18: =Assumptions!$B$22/12 | N18: =SUM(B18:M18)
A19: Total operating expenses | B19: =SUM(B14:B18) | C19: =SUM(C14:C18) | D19: =SUM(D14:D18) | E19: =SUM(E14:E18) | F19: =SUM(F14:F18) | G19: =SUM(G14:G18) | H19: =SUM(H14:H18) | I19: =SUM(I14:I18) | ... M19: =SUM(M14:M18) | N19: =SUM(B19:M19)
A20: EBITDA | B20: =B13-B19 | C20: =C13-C19 | D20: =D13-D19 | E20: =E13-E19 | F20: =F13-F19 | G20: =G13-G19 | H20: =H13-H19 | I20: =I13-I19 | ... M20: =M13-M19 | N20: =SUM(B20:M20)
A21: EBITDA margin | B21: =IF(B8=0,0,B20/B8) | C21: =IF(C8=0,0,C20/C8) | D21: =IF(D8=0,0,D20/D8) | E21: =IF(E8=0,0,E20/E8) | F21: =IF(F8=0,0,F20/F8) | G21: =IF(G8=0,0,G20/G8) | H21: =IF(H8=0,0,H20/H8) | I21: =IF(I8=0,0,I20/I8) | ... N21: =IF(N8=0,0,N20/N8)
A23: Note: 'Active subscriptions' Year-1 column shows the ending balance (a stock, not a sum).

Sheet Salesperson Bonus (MSA)
A1: JHI Research & Analytics Firm, Inc.
A2: Salesperson bonus — prepaid annual MSA (Tier 1 & 2)
A3: generated 2026-07-12 · JHI-SIG: 69M2705M
A4: Annual MSA paid up front at a prepay discount. Bonus = rate % of EBITDA (after gross margins & opex), floored at $0. Illustrative internal model.
A5: Tier 1 annual contracts (count) | B5: 50 | C5: Enterprise / Family Office, prepaid annual
A6: Tier 2 annual contracts (count) | B6: 500 | C6: Professional, prepaid annual
A7: Annual prepay discount (%) | B7: 10 | C7: Discount for paying 12 months up front
A8: Bonus rate (% of EBITDA) | B8: 10 | C8: Salesperson profit share on this book
A10: Tier 1 annual list price | B10: =Assumptions!$B$5*12
A11: Tier 1 prepaid price (net of discount) | B11: =Assumptions!$B$5*12*(1-$B$7/100)
A12: Tier 2 annual list price | B12: =Assumptions!$B$6*12
A13: Tier 2 prepaid price (net of discount) | B13: =Assumptions!$B$6*12*(1-$B$7/100)
A14: Tier 1 annual revenue | B14: =$B$5*Assumptions!$B$5*12*(1-$B$7/100)
A15: Tier 2 annual revenue | B15: =$B$6*Assumptions!$B$6*12*(1-$B$7/100)
A16: Total annual revenue (prepaid, net) | B16: =B14+B15
A17: COGS (proc+infra % + SF1) | B17: =B16*(Assumptions!$B$16+Assumptions!$B$17)/100+Assumptions!$B$18
A18: Gross profit | B18: =B16-B17
A19: Operating expenses (mktg+legal+sw+founder) | B19: =Assumptions!$B$19+Assumptions!$B$20+Assumptions!$B$21+Assumptions!$B$22
A20: EBITDA (after gross margins & opex) | B20: =B18-B19
A21: EBITDA margin | B21: =IF(B16=0,0,B20/B16)
A22: Salesperson bonus (rate % of EBITDA) | B22: =MAX(0,B20*$B$8/100)
A23: EBITDA after salesperson bonus | B23: =B20-B22
A26: Sensitivity — bonus by book volume (≈10% T1 / 90% T2)
A27: Metric | B27: 100 contracts | C27: 300 contracts | D27: 600 contracts
A28: Contracts (T1 / T2) | B28: 10 / 90 | C28: 30 / 270 | D28: 60 / 540
A29: Annual revenue (prepaid, net) | B29: =(10*Assumptions!$B$5+90*Assumptions!$B$6)*12*(1-$B$7/100) | C29: =(30*Assumptions!$B$5+270*Assumptions!$B$6)*12*(1-$B$7/100) | D29: =(60*Assumptions!$B$5+540*Assumptions!$B$6)*12*(1-$B$7/100)
A30: Gross profit | B30: =(10*Assumptions!$B$5+90*Assumptions!$B$6)*12*(1-$B$7/100)-(((10*Assumptions!$B$5+90*Assumptions!$B$6)*12*(1-$B$7/100))*(Assumptions!$B$16+Assumptions!$B$17)/100+Assumptions!$B$18) | C30: =(30*Assumptions!$B$5+270*Assumptions!$B$6)*12*(1-$B$7/100)-(((30*Assumptions!$B$5+270*Assumptions!$B$6)*12*(1-$B$7/100))*(Assumptions!$B$16+Assumptions!$B$17)/100+Assumptions!$B$18) | D30: =(60*Assumptions!$B$5+540*Assumptions!$B$6)*12*(1-$B$7/100)-(((60*Assumptions!$B$5+540*Assumptions!$B$6)*12*(1-$B$7/100))*(Assumptions!$B$16+Assumptions!$B$17)/100+Assumptions!$B$18)
A31: EBITDA | B31: =B30-(Assumptions!$B$19+Assumptions!$B$20+Assumptions!$B$21+Assumptions!$B$22) | C31: =C30-(Assumptions!$B$19+Assumptions!$B$20+Assumptions!$B$21+Assumptions!$B$22) | D31: =D30-(Assumptions!$B$19+Assumptions!$B$20+Assumptions!$B$21+Assumptions!$B$22)
A32: Salesperson bonus | B32: =MAX(0,B31*$B$8/100) | C32: =MAX(0,C31*$B$8/100) | D32: =MAX(0,D31*$B$8/100)
A34: Note: book-level EBITDA charges the full fixed annual opex to this book (conservative at low volume). Bonus floored at $0. Confirm plan mechanics with counsel/CPA.

Sheet Legal & Provenance
A1: JHI Research & Analytics Firm, Inc.
A3: Internal planning model from user-supplied assumptions — illustrative only, not a forecast, offer of employment, or compensation guarantee.
A4: Residual commission is paid on active, collected subscriptions only. Consider a residual cap / step-down and a <90-day churn clawback to protect long-term margin.
A5: Founder signature of provenance: JHI-SIG: 69M2705M
A6: © 2026 JHI Research & Analytics Firm, Inc.. All rights reserved. Confidential.
