Workbook

Sheet Disclosure
A1: John Henry Investments — Coding Disclosure by Component (Subsystem)
A2: Signature: 69M2705M | Realistic equivalent professional value of all coding performed | Rates = mid-market
A4: Subsystem | B4: Work item / action | C4: Job title (skillset) | D4: Level | E4: Hourly rate (mid, $) | F4: Est. hours | G4: Value ($) | H4: Key files | I4: Status
A5: Platform spine | B5: FastAPI app entry, router registration, CORS, /health & /ready | C5: Backend Engineer | D5: Senior | E5: 140 | F5: 10 | G5: =E5*F5 | H5: backend/app/main.py | I5: Built
A6: Platform spine | B6: Runtime settings + production fail-fast validation | C6: Backend Engineer | D6: Senior | E6: 140 | F6: 6 | G6: =E6*F6 | H6: backend/app/config.py | I6: Built
A7: Platform spine | B7: Env-gated per-IP rate-limit middleware | C7: Backend Engineer | D7: Senior | E7: 140 | F7: 6 | G7: =E7*F7 | H7: backend/app/rate_limit.py | I7: Built
A8: Platform spine | B8: DB engine/session, init_db + seeding | C8: Backend Engineer | D8: Senior | E8: 140 | F8: 10 | G8: =E8*F8 | H8: backend/app/database.py | I8: Built
A9: Platform spine | B9: SQLAlchemy ORM models (all tables) | C9: Backend Engineer | D9: Senior | E9: 140 | F9: 20 | G9: =E9*F9 | H9: backend/app/db_models.py | I9: Built
A10: Platform spine | B10: Auth dependencies (principal, require_admin) | C10: Backend Engineer | D10: Senior | E10: 140 | F10: 4 | G10: =E10*F10 | H10: backend/app/dependencies.py | I10: Built
A11: Platform spine | B11: Shared Pydantic schemas (accounting/CRM/integration) | C11: Backend Engineer | D11: Mid | E11: 140 | F11: 12 | G11: =E11*F11 | H11: backend/app/models.py | I11: Built
A12: Identity, Auth & Security | B12: Crypto primitives: PBKDF2, JWT, scoped tokens, TOTP | C12: Security Engineer | D12: Senior | E12: 190 | F12: 18 | G12: =E12*F12 | H12: backend/app/security.py | I12: Built
A13: Identity, Auth & Security | B13: Web auth API + multi-tenant register/login/me | C13: Backend Engineer | D13: Senior | E13: 140 | F13: 24 | G13: =E13*F13 | H13: routers/auth.py, foundation_services.py | I13: Built
A14: Identity, Auth & Security | B14: Mobile multi-factor (TOTP + biometric) service + API | C14: Backend Engineer | D14: Senior | E14: 140 | F14: 28 | G14: =E14*F14 | H14: routers/mobile_auth.py, mobile_services.py | I14: Built
A15: Identity, Auth & Security | B15: Encrypt TOTP secret at rest (Fernet, backward-compat) | C15: Security Engineer | D15: Senior | E15: 190 | F15: 8 | G15: =E15*F15 | H15: backend/app/security.py | I15: Built (PR #17)
A16: Identity, Auth & Security | B16: Replace hand-rolled JWT with vetted PyJWT | C16: Security Engineer | D16: Senior | E16: 190 | F16: 6 | G16: =E16*F16 | H16: backend/app/security.py | I16: Built (PR #17)
... A48: Architecture | B48: System architecture, integration & code review | C48: Tech Lead / Architect | D48: Senior | E48: 180 | F48: 20 | G48: =E48*F48 | H48: whole platform | I48: Built
D49: TOTAL | F49: =SUM(F5:F48) | G49: =SUM(G5:G48)

Sheet Rate Card
A1: Realistic Hourly Rate Card by Job Title
A2: Representative US contractor rates; anchored to docs/COMPENSATION_AND_PRO_SERVICES_PROJECTIONS.md
A4: Job title (skillset) | B4: Typical level | C4: Low ($/hr) | D4: Mid ($/hr) | E4: High ($/hr)
A5: Backend Engineer | B5: Mid–Senior | C5: 100 | D5: 140 | E5: 175
A6: Frontend Engineer | B6: Mid–Senior | C6: 85 | D6: 120 | E6: 150
A7: Security Engineer | B7: Senior | C7: 150 | D7: 190 | E7: 250
A8: Integration Engineer | B8: Senior | C8: 110 | D8: 150 | E8: 180
A9: AI Engineer | B9: Mid–Senior | C9: 150 | D9: 200 | E9: 350
A10: Data Scientist / Quant | B10: Mid–Senior | C10: 150 | D10: 200 | E10: 300
A11: DevOps / Cloud Engineer | B11: Mid–Senior | C11: 100 | D11: 160 | E11: 250
A12: QA Engineer | B12: Mid–Senior | C12: 60 | D12: 95 | E12: 120
A13: UX / UI Designer | B13: Mid–Senior | C13: 80 | D13: 120 | E13: 160
A14: Tech Lead / Architect | B14: Senior | C14: 150 | D14: 180 | E14: 250

Sheet Subsystem Summary
A1: Summary by Subsystem
A3: Subsystem | B3: Est. hours | C3: Value ($)
A4: Platform spine | B4: =SUMIF(Disclosure!$A$5:$A$48,A4,Disclosure!$F$5:$F$48) | C4: =SUMIF(Disclosure!$A$5:$A$48,A4,Disclosure!$G$5:$G$48)
A5: Identity, Auth & Security | B5: =SUMIF(Disclosure!$A$5:$A$48,A5,Disclosure!$F$5:$F$48) | C5: =SUMIF(Disclosure!$A$5:$A$48,A5,Disclosure!$G$5:$G$48)
A6: Billing & Subscriptions | B6: =SUMIF(Disclosure!$A$5:$A$48,A6,Disclosure!$F$5:$F$48) | C6: =SUMIF(Disclosure!$A$5:$A$48,A6,Disclosure!$G$5:$G$48)
A7: Accounting & Reporting | B7: =SUMIF(Disclosure!$A$5:$A$48,A7,Disclosure!$F$5:$F$48) | C7: =SUMIF(Disclosure!$A$5:$A$48,A7,Disclosure!$G$5:$G$48)
A8: CRM | B8: =SUMIF(Disclosure!$A$5:$A$48,A8,Disclosure!$F$5:$F$48) | C8: =SUMIF(Disclosure!$A$5:$A$48,A8,Disclosure!$G$5:$G$48)
A9: Market Data | B9: =SUMIF(Disclosure!$A$5:$A$48,A9,Disclosure!$F$5:$F$48) | C9: =SUMIF(Disclosure!$A$5:$A$48,A9,Disclosure!$G$5:$G$48)
A10: Research & Opportunity Score | B10: =SUMIF(Disclosure!$A$5:$A$48,A10,Disclosure!$F$5:$F$48) | C10: =SUMIF(Disclosure!$A$5:$A$48,A10,Disclosure!$G$5:$G$48)
A11: Valuations | B11: =SUMIF(Disclosure!$A$5:$A$48,A11,Disclosure!$F$5:$F$48) | C11: =SUMIF(Disclosure!$A$5:$A$48,A11,Disclosure!$G$5:$G$48)
A12: Support & AI Agents | B12: =SUMIF(Disclosure!$A$5:$A$48,A12,Disclosure!$F$5:$F$48) | C12: =SUMIF(Disclosure!$A$5:$A$48,A12,Disclosure!$G$5:$G$48)
A13: Growth / Leads | B13: =SUMIF(Disclosure!$A$5:$A$48,A13,Disclosure!$F$5:$F$48) | C13: =SUMIF(Disclosure!$A$5:$A$48,A13,Disclosure!$G$5:$G$48)
A14: External Integrations | B14: =SUMIF(Disclosure!$A$5:$A$48,A14,Disclosure!$F$5:$F$48) | C14: =SUMIF(Disclosure!$A$5:$A$48,A14,Disclosure!$G$5:$G$48)
A15: Frontend shell | B15: =SUMIF(Disclosure!$A$5:$A$48,A15,Disclosure!$F$5:$F$48) | C15: =SUMIF(Disclosure!$A$5:$A$48,A15,Disclosure!$G$5:$G$48)
... A18: Architecture | B18: =SUMIF(Disclosure!$A$5:$A$48,A18,Disclosure!$F$5:$F$48) | C18: =SUMIF(Disclosure!$A$5:$A$48,A18,Disclosure!$G$5:$G$48)
A19: TOTAL | B19: =SUM(B4:B18) | C19: =SUM(C4:C18)

Sheet By Job Title
A1: Summary by Job Title (skillset)
A3: Job title (skillset) | B3: Actions | C3: Est. hours | D3: Value ($) | E3: Mid rate ($/hr)
A4: Backend Engineer | B4: =COUNTIF(Disclosure!$C$5:$C$48,A4) | C4: =SUMIF(Disclosure!$C$5:$C$48,A4,Disclosure!$F$5:$F$48) | D4: =SUMIF(Disclosure!$C$5:$C$48,A4,Disclosure!$G$5:$G$48) | E4: 140
A5: Security Engineer | B5: =COUNTIF(Disclosure!$C$5:$C$48,A5) | C5: =SUMIF(Disclosure!$C$5:$C$48,A5,Disclosure!$F$5:$F$48) | D5: =SUMIF(Disclosure!$C$5:$C$48,A5,Disclosure!$G$5:$G$48) | E5: 190
A6: Frontend Engineer | B6: =COUNTIF(Disclosure!$C$5:$C$48,A6) | C6: =SUMIF(Disclosure!$C$5:$C$48,A6,Disclosure!$F$5:$F$48) | D6: =SUMIF(Disclosure!$C$5:$C$48,A6,Disclosure!$G$5:$G$48) | E6: 120
A7: Integration Engineer | B7: =COUNTIF(Disclosure!$C$5:$C$48,A7) | C7: =SUMIF(Disclosure!$C$5:$C$48,A7,Disclosure!$F$5:$F$48) | D7: =SUMIF(Disclosure!$C$5:$C$48,A7,Disclosure!$G$5:$G$48) | E7: 150
A8: Data Scientist / Quant | B8: =COUNTIF(Disclosure!$C$5:$C$48,A8) | C8: =SUMIF(Disclosure!$C$5:$C$48,A8,Disclosure!$F$5:$F$48) | D8: =SUMIF(Disclosure!$C$5:$C$48,A8,Disclosure!$G$5:$G$48) | E8: 200
A9: AI Engineer | B9: =COUNTIF(Disclosure!$C$5:$C$48,A9) | C9: =SUMIF(Disclosure!$C$5:$C$48,A9,Disclosure!$F$5:$F$48) | D9: =SUMIF(Disclosure!$C$5:$C$48,A9,Disclosure!$G$5:$G$48) | E9: 200
A10: UX / UI Designer | B10: =COUNTIF(Disclosure!$C$5:$C$48,A10) | C10: =SUMIF(Disclosure!$C$5:$C$48,A10,Disclosure!$F$5:$F$48) | D10: =SUMIF(Disclosure!$C$5:$C$48,A10,Disclosure!$G$5:$G$48) | E10: 120
A11: QA Engineer | B11: =COUNTIF(Disclosure!$C$5:$C$48,A11) | C11: =SUMIF(Disclosure!$C$5:$C$48,A11,Disclosure!$F$5:$F$48) | D11: =SUMIF(Disclosure!$C$5:$C$48,A11,Disclosure!$G$5:$G$48) | E11: 95
A12: DevOps / Cloud Engineer | B12: =COUNTIF(Disclosure!$C$5:$C$48,A12) | C12: =SUMIF(Disclosure!$C$5:$C$48,A12,Disclosure!$F$5:$F$48) | D12: =SUMIF(Disclosure!$C$5:$C$48,A12,Disclosure!$G$5:$G$48) | E12: 160
A13: Tech Lead / Architect | B13: =COUNTIF(Disclosure!$C$5:$C$48,A13) | C13: =SUMIF(Disclosure!$C$5:$C$48,A13,Disclosure!$F$5:$F$48) | D13: =SUMIF(Disclosure!$C$5:$C$48,A13,Disclosure!$G$5:$G$48) | E13: 180
A14: TOTAL | B14: =SUM(B4:B13) | C14: =SUM(C4:C13) | D14: =SUM(D4:D13)

Sheet Notes & Disclosure
A1: Methodology & Full Disclosure
A3: Purpose: Full disclosure of all coding performed on the JHI platform, organized by
A4: component (subsystem), mapped to the skillset / job title that would perform the work,
A5: with a realistic hourly value per action and the estimated equivalent professional value.
A7: Methodology:
A8: - 'Est. hours' = good-faith estimate of equivalent professional effort to build the
A9: delivered code (not stopwatch time). The platform was built founder-led with AI
A10: assistance, which compresses calendar time; this workbook expresses the market-rate
A11: value of the equivalent professional work product.
A12: - 'Hourly rate (mid)' = mid-market US contractor rate for that job title (see Rate Card).
A13: - 'Value' = rate x hours (computed by formula).
A14: - Job titles map to the skillset most appropriate to each action (see
... A28: Founder signature: 69M2705M | John Henry Investments (proprietary)
